binmao_libs_quart/__init__.py
binmao_libs_quart/config.py
binmao_libs_quart/db.py
binmao_libs_quart/hello.py
binmao_libs_quart/https.py
binmao_libs_quart/model.py
binmao_libs_quart/oss.py
binmao_libs_quart-0.0.1.dist-info/LICENSE
binmao_libs_quart-0.0.1.dist-info/METADATA
binmao_libs_quart-0.0.1.dist-info/WHEEL
binmao_libs_quart-0.0.1.dist-info/top_level.txt
binmao_libs_quart-0.0.1.dist-info/RECORD
