Metadata-Version: 2.1
Name: binmao_libs_quart
Version: 0.0.1
Summary: binmao linbs
Author-email: chishijie <chishijie85@gmail.com>
Classifier: Programming Language :: Python :: 3
Classifier: License :: OSI Approved :: MIT License
Classifier: Operating System :: OS Independent
Requires-Python: >=3.10
License-File: LICENSE
Requires-Dist: quart ==0.19.6
Requires-Dist: quart-schema ==0.20.0
Requires-Dist: peewee >=3.16.3
Requires-Dist: prometheus-flask-exporter >=0.22.4
Requires-Dist: qiniu >=7.11.1
Requires-Dist: PyYAML >=6.0.1
